py_code_improver/__init__.py
py_code_improver/cli.py
py_code_improver/code_improver.py
py_code_improver/prompt_templates.py
py_code_improver/tests/test_code_improver.py
py_code_improver-0.2.1.dist-info/LICENSE
py_code_improver-0.2.1.dist-info/METADATA
py_code_improver-0.2.1.dist-info/WHEEL
py_code_improver-0.2.1.dist-info/entry_points.txt
py_code_improver-0.2.1.dist-info/RECORD
