Metadata-Version: 2.1
Name: py_code_improver
Version: 0.2.1
Summary: utility to suggest code refactoring
Home-page: https://github.com/polovinko1980/llm-code-cleaner
License: MIT
Author: Alex Polovinko
Author-email: alex.polovinko@gmail.com
Maintainer: Alex Polovinko
Maintainer-email: alex.polovinko@gmail.com
Classifier: License :: OSI Approved :: MIT License
Classifier: Programming Language :: Python :: 2
Classifier: Programming Language :: Python :: 2.7
Classifier: Programming Language :: Python :: 3
Classifier: Programming Language :: Python :: 3.4
Classifier: Programming Language :: Python :: 3.5
Classifier: Programming Language :: Python :: 3.6
Classifier: Programming Language :: Python :: 3.7
Classifier: Programming Language :: Python :: 3.8
Classifier: Programming Language :: Python :: 3.9
Classifier: Programming Language :: Python :: 3.10
Classifier: Programming Language :: Python :: 3.11
Classifier: Programming Language :: Python :: 3.12
Requires-Dist: langchain_core (>=0.3.15,<0.4.0)
Requires-Dist: langchain_openai (>=0.2.2,<0.3.0)
Requires-Dist: openai (>=1.55.3,<2.0.0)
Project-URL: Repository, https://github.com/polovinko1980/llm-code-cleaner
